{
    "automatic_switch_1": {
        "description": "Settings for the first automatic switch",
        "options":[
            "None","Idle (Default State)","Open For Entry","Always Open For Entry",
            "Open For Exit","Always Open For Exit","Close For Exit"
        ],
        "on_trigger": "",
        "on_release": ""
    },
    "automatic_switch_2": {
        "description": "Settings for the second automatic switch",
        "options":[
            "None","Idle (Default State)","Open For Entry","Always Open For Entry",
            "Open For Exit","Always Open For Exit","Close For Exit"
        ],
        "on_trigger": "",
        "on_release": ""
    },
    "fire_alarm": {
        "description": "Settings for the fire alarm system",
        "options":[
            "None","Idle (Default State)","Open For Entry","Always Open For Entry",
            "Close For Entry","Open For Exit","Always Open For Exit","Close For Exit"
        ],
        "on_trigger": "",
        "on_release": ""
    },
    "manual_switch": {
        "description": "Settings for the manual switch",
       "options":[
            "None","Idle (Default State)","Open For Entry","Always Open For Entry",
            "Open For Exit","Always Open For Exit","Close For Exit"
        ],
        "on_trigger": "",
        "on_release": ""
    }
}
